domain/__init__.py
domain/bipedal_walker.py
domain/cartpole_swingup.py
domain/classify_gym.py
domain/config.py
domain/hyperparameters.py
domain/make_env.py
domain/task_gym.py
domain/vae_racing.py
prettyNEAT/__init__.py
prettyNEAT/_speciate.py
prettyNEAT/_variation.py
prettyNEAT/ann.py
prettyNEAT/dataGatherer.py
prettyNEAT/ind.py
prettyNEAT/neat.py
prettyNEAT/nsga_sort.py
prettyNEAT/utils.py
utils/__init__.py
utils/utils.py
vis/__init__.py
vis/lplot.py
vis/neatVis.py
vis/viewInd.py
prettyNEAT-0.0.1.dist-info/LICENSE
prettyNEAT-0.0.1.dist-info/METADATA
prettyNEAT-0.0.1.dist-info/WHEEL
prettyNEAT-0.0.1.dist-info/top_level.txt
prettyNEAT-0.0.1.dist-info/RECORD
