Metadata-Version: 2.1
Name: prettyNEAT
Version: 0.0.1
Summary: NeuroEvolution of Augmenting Topologies in Python
Home-page: https://github.com/d9w/prettyNEAT
Author: Dennis G. Wilson
Author-email: d9w@pm.me
License: UNKNOWN
Project-URL: Bug Tracker, https://github.com/d9w/prettyNEAT/issues
Platform: UNKNOWN
Classifier: Programming Language :: Python :: 3
Classifier: License :: OSI Approved :: Apache Software License
Classifier: Operating System :: OS Independent
Classifier: Topic :: Scientific/Engineering :: Artificial Intelligence
Classifier: Topic :: Scientific/Engineering :: Artificial Life
Requires-Python: >=3.5
Requires-Dist: numpy
Requires-Dist: json
